{"data_source": {"input": {"date": "2013-01-30", "contact": "mbruemmer@smu.edu/james.loach@gmail.com", "name": "Matthew Bruemmer / James Loach"}, "notes": "", "reference": "D.S.Leonard et al., Nucl. Instr. and Meth. A 591 (2008)(10.1016/j.nima.2008.03.001)"}, "specification": "2.01", "sample": {"owner": {"contact": "", "name": ""}, "source": "", "id": "Table 3. #123", "description": "MRC Al for APDs 20-101E-AL000-1000, purity grade 99.9995", "name": "Aluminum, for APDs, 99.9995, MRC"}, "measurement": {"practitioner": {"contact": "", "name": ""}, "description": "For each of K, Th, and U, natural terrestrial abundance ratios were used to covert from isotopic to total elemental abundances.", "technique": "NAA", "results": [{"isotope": "K", "type": "limit", "value": [68000, 95], "unit": "ppb"}, {"isotope": "Th", "type": "measurement", "value": [48000, 4800], "unit": "ppt"}, {"isotope": "U", "type": "measurement", "value": [5500, 580], "unit": "ppt"}], "requestor": {"contact": "", "name": ""}, "date": [], "institution": ""}, "_id": "2b49e6fb705f21c6c861b2a8ae20ad1c", "type": "measurement", "sort_indices": {"u": 5500.0, "th": 48000.0}, "grouping": "EXO (2008)"}